bcc/__init__.py
bcc/bcc.py
bcc-0.1.8.dist-info/DESCRIPTION.rst
bcc-0.1.8.dist-info/METADATA
bcc-0.1.8.dist-info/RECORD
bcc-0.1.8.dist-info/WHEEL
bcc-0.1.8.dist-info/metadata.json
bcc-0.1.8.dist-info/top_level.txt
